biolinkml/__init__.py
biolinkml/meta.py
biolinkml/dumpers/__init__.py
biolinkml/dumpers/json_dumper.py
biolinkml/dumpers/rdf_dumper.py
biolinkml/dumpers/yaml_dumper.py
biolinkml/generators/PythonGenNotes.md
biolinkml/generators/README.md
biolinkml/generators/__init__.py
biolinkml/generators/csvgen.py
biolinkml/generators/dotgen.py
biolinkml/generators/golrgen.py
biolinkml/generators/graphqlgen.py
biolinkml/generators/infer_model.py
biolinkml/generators/jsonldcontextgen.py
biolinkml/generators/jsonldgen.py
biolinkml/generators/jsonschemagen.py
biolinkml/generators/lpgen.py
biolinkml/generators/markdowngen.py
biolinkml/generators/namespacegen.py
biolinkml/generators/owlgen.py
biolinkml/generators/prefixmapgen.py
biolinkml/generators/protogen.py
biolinkml/generators/pythongen.py
biolinkml/generators/rdfgen.py
biolinkml/generators/shexgen.py
biolinkml/generators/string_template.md
biolinkml/generators/summarygen.py
biolinkml/generators/yamlgen.py
biolinkml/generators/yumlgen.py
biolinkml/loaders/__init__.py
biolinkml/loaders/context_flattener.py
biolinkml/loaders/document_loader.py
biolinkml/loaders/json_loader.py
biolinkml/loaders/loader_root.py
biolinkml/loaders/rdf_loader.py
biolinkml/loaders/requests_ssl_patch.py
biolinkml/loaders/yaml_loader.py
biolinkml/services/__init__.py
biolinkml/services/tccm_mockup.py
biolinkml/services/tccm_obo_filter.py
biolinkml/utils/__init__.py
biolinkml/utils/comparefiles.py
biolinkml/utils/compile_python.py
biolinkml/utils/context_utils.py
biolinkml/utils/curienamespace.py
biolinkml/utils/dataclass_extensions_375.py
biolinkml/utils/dataclass_extensions_376.py
biolinkml/utils/enumerations.py
biolinkml/utils/formatutils.py
biolinkml/utils/generator.py
biolinkml/utils/ifabsent_functions.py
biolinkml/utils/mergeutils.py
biolinkml/utils/metamodelcore.py
biolinkml/utils/namespaces.py
biolinkml/utils/permissiblevalueimpl.py
biolinkml/utils/rawloader.py
biolinkml/utils/schemaloader.py
biolinkml/utils/schemasynopsis.py
biolinkml/utils/slot.py
biolinkml-1.7.6.dist-info/AUTHORS
biolinkml-1.7.6.dist-info/LICENSE
biolinkml-1.7.6.dist-info/METADATA
biolinkml-1.7.6.dist-info/WHEEL
biolinkml-1.7.6.dist-info/entry_points.txt
biolinkml-1.7.6.dist-info/pbr.json
biolinkml-1.7.6.dist-info/top_level.txt
biolinkml-1.7.6.dist-info/RECORD
